{
  "color": [
    {
      "name": "start_window_background",
      "value": "#FFFFFF"
    },
    {
      "name": "background_color",
      "value": "#FFFFFF"
    },
    {
      "name": "common_gray",
      "value": "#848484"
    },
    {
      "name": "common_white",
      "value": "#FFFFFF"
    },
    {
      "name": "background_color_gray",
      "value": "#f8f8f8"
    },
    {
      "name": "component_color",
      "value": "#f8f8f8"
    },
    {
      "name": "text_color",
      "value": "#000000"
    },
    {
      "name": "label_color",
      "value": "#FFE0E0E0"
    }
  ]
}